vnpy_hft/__init__.py
vnpy_hft/api/__init__.py
vnpy_hft/api/hft/__init__.py
vnpy_hft/api/hft/hft_constant.py
vnpy_hft/api/hft/libhft_trader_api.dll
vnpy_hft/api/hft/vnhfttd.cp310-win_amd64.pyd
vnpy_hft/api/hft/generator/hft_td_header_function.h
vnpy_hft/api/hft/generator/hft_td_header_on.h
vnpy_hft/api/hft/generator/hft_td_source_function.cpp
vnpy_hft/api/hft/generator/hft_td_source_module.cpp
vnpy_hft/api/hft/generator/hft_td_source_on.cpp
vnpy_hft/api/hft/generator/hft_td_source_spi.cpp
vnpy_hft/api/hft/include/hft/hft_ext_trader_api.h
vnpy_hft/api/hft/include/hft/hft_ext_trader_struct.h
vnpy_hft/api/hft/include/hft/hft_option_trader_api.h
vnpy_hft/api/hft/include/hft/hft_trader_api.h
vnpy_hft/api/hft/include/hft/hft_trader_common.h
vnpy_hft/api/hft/include/hft/hft_trader_def.h
vnpy_hft/api/hft/include/hft/hft_trader_error.h
vnpy_hft/api/hft/include/hft/hft_trader_struct.h
vnpy_hft/api/hft/include/pybind11/attr.h
vnpy_hft/api/hft/include/pybind11/buffer_info.h
vnpy_hft/api/hft/include/pybind11/cast.h
vnpy_hft/api/hft/include/pybind11/chrono.h
vnpy_hft/api/hft/include/pybind11/common.h
vnpy_hft/api/hft/include/pybind11/complex.h
vnpy_hft/api/hft/include/pybind11/eigen.h
vnpy_hft/api/hft/include/pybind11/embed.h
vnpy_hft/api/hft/include/pybind11/eval.h
vnpy_hft/api/hft/include/pybind11/functional.h
vnpy_hft/api/hft/include/pybind11/iostream.h
vnpy_hft/api/hft/include/pybind11/numpy.h
vnpy_hft/api/hft/include/pybind11/operators.h
vnpy_hft/api/hft/include/pybind11/options.h
vnpy_hft/api/hft/include/pybind11/pybind11.h
vnpy_hft/api/hft/include/pybind11/pytypes.h
vnpy_hft/api/hft/include/pybind11/stl.h
vnpy_hft/api/hft/include/pybind11/stl_bind.h
vnpy_hft/api/hft/include/pybind11/detail/class.h
vnpy_hft/api/hft/include/pybind11/detail/common.h
vnpy_hft/api/hft/include/pybind11/detail/descr.h
vnpy_hft/api/hft/include/pybind11/detail/init.h
vnpy_hft/api/hft/include/pybind11/detail/internals.h
vnpy_hft/api/hft/include/pybind11/detail/typeid.h
vnpy_hft-1.0.3.dist-info/LICENSE
vnpy_hft-1.0.3.dist-info/METADATA
vnpy_hft-1.0.3.dist-info/WHEEL
vnpy_hft-1.0.3.dist-info/top_level.txt
vnpy_hft-1.0.3.dist-info/RECORD
